{
	"file_path": "C:\\Users\\cadea\\AppData\\Local\\Packages\\Microsoft.MinecraftUWP_8wekyb3d8bbwe\\LocalState\\games\\com.mojang\\development_behavior_packs\\Endergy BP\\tags\\block_immitation.json",
	"file_type": "entity_tag",
	"format_version": 1,
	"file_uuid": "0b084550_a4b1_4496_9f62_8a072155d218",
	"file_version": 8,
	"cache_content": {
		"children": [
			{
				"open": {
					"bridge:tag": {
						"description": {
							"identifier": "endergy:block_immitation"
						},
						"component_groups": {},
						"components": {
							"minecraft:health": {
								"value": 1,
								"max": 1
							},
							"minecraft:physics": {
								"has_collision": false,
								"has_gravity": false
							},
							"minecraft:damage_sensor": {
								"triggers": [
									{
										"on_damage": {
											"filters": {
												"all_of": [
													{
														"subject": "other",
														"test": "is_family",
														"value": "player"
													}
												]
											}
										}
									},
									{
										"deals_damage": false
									}
								]
							},
							"minecraft:pushable": {
								"is_pushable": false,
								"is_pushable_by_piston": true
							}
						},
						"events": {}
					}
				},
				"key": "bridge:tag",
				"children": [
					{
						"open": {
							"description": {
								"identifier": "endergy:block_immitation"
							},
							"component_groups": {},
							"components": {
								"minecraft:health": {
									"value": 1,
									"max": 1
								},
								"minecraft:physics": {
									"has_collision": false,
									"has_gravity": false
								},
								"minecraft:damage_sensor": {
									"triggers": [
										{
											"on_damage": {
												"filters": {
													"all_of": [
														{
															"subject": "other",
															"test": "is_family",
															"value": "player"
														}
													]
												}
											}
										},
										{
											"deals_damage": false
										}
									]
								},
								"minecraft:pushable": {
									"is_pushable": false,
									"is_pushable_by_piston": true
								}
							},
							"events": {}
						},
						"key": "description",
						"is_minified": true,
						"children": {
							"identifier": "endergy:block_immitation"
						}
					},
					{
						"open": {
							"description": {
								"identifier": "endergy:block_immitation"
							},
							"component_groups": {},
							"components": {
								"minecraft:health": {
									"value": 1,
									"max": 1
								},
								"minecraft:physics": {
									"has_collision": false,
									"has_gravity": false
								},
								"minecraft:damage_sensor": {
									"triggers": [
										{
											"on_damage": {
												"filters": {
													"all_of": [
														{
															"subject": "other",
															"test": "is_family",
															"value": "player"
														}
													]
												}
											}
										},
										{
											"deals_damage": false
										}
									]
								},
								"minecraft:pushable": {
									"is_pushable": false,
									"is_pushable_by_piston": true
								}
							},
							"events": {}
						},
						"key": "component_groups",
						"is_minified": true,
						"children": {}
					},
					{
						"open": {
							"description": {
								"identifier": "endergy:block_immitation"
							},
							"component_groups": {},
							"components": {
								"minecraft:health": {
									"value": 1,
									"max": 1
								},
								"minecraft:physics": {
									"has_collision": false,
									"has_gravity": false
								},
								"minecraft:damage_sensor": {
									"triggers": [
										{
											"on_damage": {
												"filters": {
													"all_of": [
														{
															"subject": "other",
															"test": "is_family",
															"value": "player"
														}
													]
												}
											}
										},
										{
											"deals_damage": false
										}
									]
								},
								"minecraft:pushable": {
									"is_pushable": false,
									"is_pushable_by_piston": true
								}
							},
							"events": {}
						},
						"key": "components",
						"children": [
							{
								"open": {
									"minecraft:health": {
										"value": 1,
										"max": 1
									},
									"minecraft:physics": {
										"has_collision": false,
										"has_gravity": false
									},
									"minecraft:damage_sensor": {
										"triggers": [
											{
												"on_damage": {
													"filters": {
														"all_of": [
															{
																"subject": "other",
																"test": "is_family",
																"value": "player"
															}
														]
													}
												}
											},
											{
												"deals_damage": false
											}
										]
									},
									"minecraft:pushable": {
										"is_pushable": false,
										"is_pushable_by_piston": true
									}
								},
								"key": "minecraft:health",
								"is_minified": true,
								"children": {
									"value": 1,
									"max": 1
								}
							},
							{
								"open": {
									"minecraft:health": {
										"value": 1,
										"max": 1
									},
									"minecraft:physics": {
										"has_collision": false,
										"has_gravity": false
									},
									"minecraft:damage_sensor": {
										"triggers": [
											{
												"on_damage": {
													"filters": {
														"all_of": [
															{
																"subject": "other",
																"test": "is_family",
																"value": "player"
															}
														]
													}
												}
											},
											{
												"deals_damage": false
											}
										]
									},
									"minecraft:pushable": {
										"is_pushable": false,
										"is_pushable_by_piston": true
									}
								},
								"key": "minecraft:physics",
								"is_minified": true,
								"children": {
									"has_collision": false,
									"has_gravity": false
								}
							},
							{
								"key": "minecraft:damage_sensor",
								"is_minified": true,
								"children": {
									"triggers": [
										{
											"on_damage": {
												"filters": {
													"all_of": [
														{
															"subject": "other",
															"test": "is_family",
															"value": "player"
														}
													]
												}
											}
										},
										{
											"deals_damage": false
										}
									]
								}
							},
							{
								"open": {
									"minecraft:health": {
										"value": 1,
										"max": 1
									},
									"minecraft:physics": {
										"has_collision": false,
										"has_gravity": false
									},
									"minecraft:damage_sensor": {
										"triggers": [
											{
												"on_damage": {
													"filters": {
														"all_of": [
															{
																"subject": "other",
																"test": "is_family",
																"value": "player"
															}
														]
													}
												}
											},
											{
												"deals_damage": false
											}
										]
									},
									"minecraft:pushable": {
										"is_pushable": false,
										"is_pushable_by_piston": true
									}
								},
								"key": "minecraft:pushable",
								"is_minified": true,
								"children": {
									"is_pushable": false,
									"is_pushable_by_piston": true
								}
							}
						]
					},
					{
						"open": {
							"description": {
								"identifier": "endergy:block_immitation"
							},
							"component_groups": {},
							"components": {
								"minecraft:health": {
									"value": 1,
									"max": 1
								},
								"minecraft:physics": {
									"has_collision": false,
									"has_gravity": false
								},
								"minecraft:damage_sensor": {
									"triggers": [
										{
											"on_damage": {
												"filters": {
													"all_of": [
														{
															"subject": "other",
															"test": "is_family",
															"value": "player"
														}
													]
												}
											}
										},
										{
											"deals_damage": false
										}
									]
								},
								"minecraft:pushable": {
									"is_pushable": false,
									"is_pushable_by_piston": true
								}
							},
							"events": {}
						},
						"key": "events",
						"is_minified": true,
						"children": {}
					}
				]
			}
		]
	}
}